setup.py
salure_helpers/salure_functions/__init__.py
salure_helpers/salure_functions/salure_functions.py
salure_helpers_salure_functions.egg-info/PKG-INFO
salure_helpers_salure_functions.egg-info/SOURCES.txt
salure_helpers_salure_functions.egg-info/dependency_links.txt
salure_helpers_salure_functions.egg-info/not-zip-safe
salure_helpers_salure_functions.egg-info/requires.txt
salure_helpers_salure_functions.egg-info/top_level.txt