Metadata-Version: 1.0
Name: salure-helpers-salure-functions
Version: 2.2.2
Summary: Helpful functions from Salure
Home-page: UNKNOWN
Author: D&A Salure
Author-email: support@salureconnnect.com
License: Salure License
Platform: UNKNOWN
